flamehaven_doc_sanity/__init__.py
flamehaven_doc_sanity/cli.py
flamehaven_doc_sanity/cli_translate.py
flamehaven_doc_sanity/exceptions.py
flamehaven_doc_sanity/config/__init__.py
flamehaven_doc_sanity/config/golden_baseline.yaml
flamehaven_doc_sanity/config/policies.yaml
flamehaven_doc_sanity/dashboard/__init__.py
flamehaven_doc_sanity/dashboard/server.py
flamehaven_doc_sanity/dashboard/static/css/dashboard.css
flamehaven_doc_sanity/dashboard/static/js/dashboard.js
flamehaven_doc_sanity/dashboard/templates/dashboard.html
flamehaven_doc_sanity/governance/__init__.py
flamehaven_doc_sanity/governance/driftlock_guard.py
flamehaven_doc_sanity/governance/hope_guard.py
flamehaven_doc_sanity/governance/policy_enforcer.py
flamehaven_doc_sanity/governance/tribunal_engine.py
flamehaven_doc_sanity/i18n/__init__.py
flamehaven_doc_sanity/i18n/code_comment_parser.py
flamehaven_doc_sanity/i18n/language_detector.py
flamehaven_doc_sanity/i18n/metacognition.py
flamehaven_doc_sanity/i18n/translator.py
flamehaven_doc_sanity/orchestrator/__init__.py
flamehaven_doc_sanity/orchestrator/fusion_oracle.py
flamehaven_doc_sanity/orchestrator/modal_router.py
flamehaven_doc_sanity/performance/__init__.py
flamehaven_doc_sanity/plugins/__init__.py
flamehaven_doc_sanity/plugins/base.py
flamehaven_doc_sanity/plugins/loader.py
flamehaven_doc_sanity/plugins/registry.py
flamehaven_doc_sanity/plugins/samples/__init__.py
flamehaven_doc_sanity/plugins/samples/json_formatter.py
flamehaven_doc_sanity/plugins/samples/markdown_validator.py
flamehaven_doc_sanity/plugins/samples/security_governance.py
flamehaven_doc_sanity/validators/__init__.py
flamehaven_doc_sanity-1.3.0.dist-info/licenses/LICENSE
flamehaven_doc_sanity-1.3.0.dist-info/METADATA
flamehaven_doc_sanity-1.3.0.dist-info/WHEEL
flamehaven_doc_sanity-1.3.0.dist-info/entry_points.txt
flamehaven_doc_sanity-1.3.0.dist-info/top_level.txt
flamehaven_doc_sanity-1.3.0.dist-info/RECORD
