Metadata-Version: 2.4
Name: flamehaven-doc-sanity
Version: 1.3.0
Summary: Ω-Grade Documentation Governance & Validation System with I18n, Drift Detection, and Plugin Architecture
Author-email: Flamehaven <flamehaven01@users.noreply.github.com>
Project-URL: Homepage, https://github.com/flamehaven01/Flamehaven-Doc-Sanity
Project-URL: Documentation, https://github.com/flamehaven01/Flamehaven-Doc-Sanity#readme
Project-URL: Repository, https://github.com/flamehaven01/Flamehaven-Doc-Sanity
Project-URL: Changelog, https://github.com/flamehaven01/Flamehaven-Doc-Sanity/blob/main/CHANGELOG.md
Project-URL: Bug Tracker, https://github.com/flamehaven01/Flamehaven-Doc-Sanity/issues
Keywords: documentation,governance,validation,drift-detection,i18n,translation,quality-assurance,plugin-system,ci-cd
Classifier: Development Status :: 5 - Production/Stable
Classifier: Intended Audience :: Developers
Classifier: License :: OSI Approved :: MIT License
Classifier: Operating System :: OS Independent
Classifier: Programming Language :: Python :: 3
Classifier: Programming Language :: Python :: 3.9
Classifier: Programming Language :: Python :: 3.10
Classifier: Programming Language :: Python :: 3.11
Classifier: Programming Language :: Python :: 3.12
Classifier: Topic :: Software Development :: Quality Assurance
Classifier: Topic :: Software Development :: Documentation
Classifier: Topic :: Software Development :: Testing
Classifier: Typing :: Typed
Requires-Python: >=3.9
License-File: LICENSE
Requires-Dist: click>=8.0.0
Requires-Dist: pyyaml>=6.0
Provides-Extra: dev
Requires-Dist: pytest>=7.0.0; extra == "dev"
Requires-Dist: pytest-cov>=4.0.0; extra == "dev"
Requires-Dist: black>=23.0.0; extra == "dev"
Requires-Dist: isort>=5.12.0; extra == "dev"
Requires-Dist: flake8>=6.0.0; extra == "dev"
Requires-Dist: mypy>=1.0.0; extra == "dev"
Requires-Dist: pre-commit>=3.0.0; extra == "dev"
Provides-Extra: dashboard
Requires-Dist: flask>=2.3.0; extra == "dashboard"
Provides-Extra: all
Requires-Dist: pytest>=7.0.0; extra == "all"
Requires-Dist: pytest-cov>=4.0.0; extra == "all"
Requires-Dist: black>=23.0.0; extra == "all"
Requires-Dist: isort>=5.12.0; extra == "all"
Requires-Dist: flake8>=6.0.0; extra == "all"
Requires-Dist: mypy>=1.0.0; extra == "all"
Requires-Dist: pre-commit>=3.0.0; extra == "all"
Requires-Dist: flask>=2.3.0; extra == "all"
Dynamic: license-file
